{
    "faults": [
        1,
        2,
        3,
        4,
        5,
        6,
        7,
        8,
        9,
        10
    ],
    "results": [
        55.00000000000001,
        5.0,
        3.0,
        2.0,
        0.0,
        0.0,
        0.0,
        0.0,
        0.0,
        0.0
    ],
    "date": "2025-05-15 23:17:24.556484+10:00",
    "verilog_file_hash": "692f4796fbadb83c27250cddb9fccb6702b45634fc028b58f6d03c4ea6e38dd2",
    "num_faults": 10,
    "verilog_path": "../tests/verilog/not_tmr.sv",
    "top": "not_tmr",
    "samples": 100,
    "type_": "unprotected"
}